async_rithmic/__init__.py
async_rithmic/client.py
async_rithmic/enums.py
async_rithmic/exceptions.py
async_rithmic/logger.py
async_rithmic/objects.py
async_rithmic/certificates/rithmic_ssl_cert_auth_params
async_rithmic/helpers/background_task_mixin.py
async_rithmic/helpers/concurrency.py
async_rithmic/helpers/connectivity.py
async_rithmic/helpers/request_manager.py
async_rithmic/plants/__init__.py
async_rithmic/plants/base.py
async_rithmic/plants/history.py
async_rithmic/plants/order.py
async_rithmic/plants/pnl.py
async_rithmic/plants/ticker.py
async_rithmic/protocol_buffers/__init__.py
async_rithmic/protocol_buffers/account_pnl_position_update_pb2.py
async_rithmic/protocol_buffers/base_pb2.py
async_rithmic/protocol_buffers/best_bid_offer_pb2.py
async_rithmic/protocol_buffers/bracket_updates_pb2.py
async_rithmic/protocol_buffers/depth_by_order_end_event_pb2.py
async_rithmic/protocol_buffers/depth_by_order_pb2.py
async_rithmic/protocol_buffers/exchange_order_notification_pb2.py
async_rithmic/protocol_buffers/forced_logout_pb2.py
async_rithmic/protocol_buffers/instrument_pnl_position_update_pb2.py
async_rithmic/protocol_buffers/last_trade_pb2.py
async_rithmic/protocol_buffers/order_book_pb2.py
async_rithmic/protocol_buffers/reject_pb2.py
async_rithmic/protocol_buffers/request_account_list_pb2.py
async_rithmic/protocol_buffers/request_account_rms_info_pb2.py
async_rithmic/protocol_buffers/request_bracket_order_pb2.py
async_rithmic/protocol_buffers/request_cancel_all_orders_pb2.py
async_rithmic/protocol_buffers/request_cancel_order_pb2.py
async_rithmic/protocol_buffers/request_depth_by_order_snapshot_pb2.py
async_rithmic/protocol_buffers/request_depth_by_order_updates_pb2.py
async_rithmic/protocol_buffers/request_exit_position_pb2.py
async_rithmic/protocol_buffers/request_front_month_contract_pb2.py
async_rithmic/protocol_buffers/request_heartbeat_pb2.py
async_rithmic/protocol_buffers/request_list_exchange_permissions_pb2.py
async_rithmic-1.5.6.dist-info/licenses/LICENSE
async_rithmic-1.5.6.dist-info/METADATA
async_rithmic-1.5.6.dist-info/WHEEL
async_rithmic-1.5.6.dist-info/top_level.txt
async_rithmic-1.5.6.dist-info/RECORD
