Metadata-Version: 2.4
Name: async_rithmic
Version: 1.5.6
Summary: Python API Integration with Rithmic Protocol Buffer API
Author: Mickael Burguet
License: MIT
Project-URL: Homepage, https://github.com/rundef/async_rithmic
Project-URL: Repository, https://github.com/rundef/async_rithmic
Project-URL: Issues, https://github.com/rundef/async_rithmic/issues
Keywords: python,rithmic
Classifier: Development Status :: 5 - Production/Stable
Classifier: Intended Audience :: Developers
Classifier: Topic :: Software Development :: Build Tools
Classifier: Programming Language :: Python :: 3
Classifier: Programming Language :: Python :: 3.10
Classifier: Programming Language :: Python :: 3.11
Classifier: Programming Language :: Python :: 3.12
Classifier: Programming Language :: Python :: 3.13
Classifier: Programming Language :: Python :: 3 :: Only
Classifier: License :: OSI Approved :: MIT License
Classifier: Operating System :: OS Independent
Requires-Python: >=3.10
License-File: LICENSE
Requires-Dist: pattern_kit>=2.0.0
Requires-Dist: websockets<15.0,>=11.0
Requires-Dist: protobuf<5,>=4.25.4
Requires-Dist: pytz>=2022.5
Requires-Dist: tzlocal>=5.2
Provides-Extra: dev
Requires-Dist: check-manifest; extra == "dev"
Provides-Extra: test
Requires-Dist: coverage; extra == "test"
Requires-Dist: pytest; extra == "test"
Dynamic: license-file
